{"post":{"summary":"Удалить записи (form-data)","requestBody":{"required":true,"content":{"multipart/form-data":{"schema":{"type":"object","properties":{"table":{"type":"string","description":"Имя таблицы"},"filter":{"type":"object","description":"Массив фильтров. См. ПолучитьСтруктуруФильтраЗаписей (необяз. по ум. - Пустое значение)"},"db":{"type":"string","description":"Существующее соединение или путь к базе (необяз. по ум. - Пустое значение)"}},"required":["table"]}}}},"responses":{"200":{"description":"Успешный ответ","content":{"application/json":{"schema":{"type":"object","properties":{"result":{"type":"boolean","description":"Флаг успешности"},"data":{"type":"object","description":"Данные результата"}}}}}}},"tags":["sqlite"]}}