{"get":{"summary":"Выполнение через метод GET","parameters":[{"name":"token","in":"query","schema":{"type":"string"},"description":"Токен"},{"name":"url","in":"query","schema":{"type":"string"},"description":"Адрес объекта"},{"name":"path","in":"query","schema":{"type":"string"},"description":"Путь внутри объекта (необяз. по ум. - Пустое значение)"}],"responses":{"200":{"description":"Успешный ответ","content":{"application/json":{"schema":{"type":"object","properties":{"result":{"type":"boolean","description":"Флаг успешности"},"data":{"type":"object","description":"Данные результата"}}}}}}},"tags":["yadisk"]},"post":{"summary":"Выполнение через метод POST (JSON или form-data)","requestBody":{"required":true,"content":{"multipart/form-data":{"schema":{"type":"object","properties":{"token":{"type":"string","description":"Токен"},"url":{"type":"string","description":"Адрес объекта"},"path":{"type":"string","description":"Путь внутри объекта (необяз. по ум. - Пустое значение)"}},"required":["token","url"]}},"application/json":{"schema":{"type":"object","properties":{"token":{"type":"string","description":"Токен"},"url":{"type":"string","description":"Адрес объекта"},"path":{"type":"string","description":"Путь внутри объекта (необяз. по ум. - Пустое значение)"}},"required":["token","url"]}}}},"responses":{"200":{"description":"Успешный ответ","content":{"application/json":{"schema":{"type":"object","properties":{"result":{"type":"boolean","description":"Флаг успешности"},"data":{"type":"object","description":"Данные результата"}}}}}}},"tags":["yadisk"]}}