{"get":{"summary":"Выполнение через метод GET","parameters":[{"name":"token","in":"query","schema":{"type":"string"},"description":"Токен"},{"name":"from","in":"query","schema":{"type":"string"},"description":"Путь к оригинальному файлу или каталогу"},{"name":"to","in":"query","schema":{"type":"string"},"description":"Путь назначения для копии"},{"name":"rewrite","in":"query","schema":{"type":"boolean"},"description":"Перезаписывать если файл с таким именем уже существует (необяз. по ум. - Нет)"}],"responses":{"200":{"description":"Успешный ответ","content":{"application/json":{"schema":{"type":"object","properties":{"result":{"type":"boolean","description":"Флаг успешности"},"data":{"type":"object","description":"Данные результата"}}}}}}}},"post":{"summary":"Выполнение через метод POST (JSON или form-data)","requestBody":{"required":true,"content":{"multipart/form-data":{"schema":{"type":"object","properties":{"token":{"type":"string","description":"Токен"},"from":{"type":"string","description":"Путь к оригинальному файлу или каталогу"},"to":{"type":"string","description":"Путь назначения для копии"},"rewrite":{"type":"boolean","description":"Перезаписывать если файл с таким именем уже существует (необяз. по ум. - Нет)"}},"required":["token","from","to"]}},"application/json":{"schema":{"type":"object","properties":{"token":{"type":"string","description":"Токен"},"from":{"type":"string","description":"Путь к оригинальному файлу или каталогу"},"to":{"type":"string","description":"Путь назначения для копии"},"rewrite":{"type":"boolean","description":"Перезаписывать если файл с таким именем уже существует (необяз. по ум. - Нет)"}},"required":["token","from","to"]}}}},"responses":{"200":{"description":"Успешный ответ","content":{"application/json":{"schema":{"type":"object","properties":{"result":{"type":"boolean","description":"Флаг успешности"},"data":{"type":"object","description":"Данные результата"}}}}}}}}}